{
"meta":{"test_sets":[],"test_metrics":[],"learn_metrics":[{"best_value":"Min","name":"RMSE"}],"launch_mode":"Train","parameters":"","iteration_count":100,"learn_sets":["learn"],"name":"experiment"},
"iterations":[
{"learn":[14.005006],"iteration":0,"passed_time":0.001753295834,"remaining_time":0.1735762876},
{"learn":[13.14441192],"iteration":1,"passed_time":0.003227949013,"remaining_time":0.1581695016},
{"learn":[12.34258257],"iteration":2,"passed_time":0.004598069259,"remaining_time":0.148670906},
{"learn":[11.64527793],"iteration":3,"passed_time":0.005671315075,"remaining_time":0.1361115618},
{"learn":[11.02766183],"iteration":4,"passed_time":0.007138278847,"remaining_time":0.1356272981},
{"learn":[10.43485794],"iteration":5,"passed_time":0.008674414204,"remaining_time":0.1358991559},
{"learn":[9.890641275],"iteration":6,"passed_time":0.01024504616,"remaining_time":0.1361127561},
{"learn":[9.492161212],"iteration":7,"passed_time":0.01156248765,"remaining_time":0.132968608},
{"learn":[9.105082953],"iteration":8,"passed_time":0.01294219928,"remaining_time":0.1308600149},
{"learn":[8.674157135],"iteration":9,"passed_time":0.0142948509,"remaining_time":0.1286536581},
{"learn":[8.341743544],"iteration":10,"passed_time":0.01583662248,"remaining_time":0.1281326728},
{"learn":[8.049372916],"iteration":11,"passed_time":0.01737463972,"remaining_time":0.1274140246},
{"learn":[7.757318612],"iteration":12,"passed_time":0.01883508126,"remaining_time":0.1260501592},
{"learn":[7.522206899],"iteration":13,"passed_time":0.02024776673,"remaining_time":0.1243791385},
{"learn":[7.297756655],"iteration":14,"passed_time":0.02160543673,"remaining_time":0.1224308081},
{"learn":[7.088359431],"iteration":15,"passed_time":0.02289946858,"remaining_time":0.1202222101},
{"learn":[6.882113791],"iteration":16,"passed_time":0.02422738865,"remaining_time":0.1182866622},
{"learn":[6.704728832],"iteration":17,"passed_time":0.02554369604,"remaining_time":0.1163657264},
{"learn":[6.563881962],"iteration":18,"passed_time":0.02686554278,"remaining_time":0.1145320508},
{"learn":[6.418790279],"iteration":19,"passed_time":0.02821246722,"remaining_time":0.1128498689},
{"learn":[6.315756953],"iteration":20,"passed_time":0.02962386974,"remaining_time":0.1114421766},
{"learn":[6.210157751],"iteration":21,"passed_time":0.03121612631,"remaining_time":0.1106753569},
{"learn":[6.115058449],"iteration":22,"passed_time":0.03269394432,"remaining_time":0.1094536397},
{"learn":[6.014819884],"iteration":23,"passed_time":0.03399870166,"remaining_time":0.1076625552},
{"learn":[5.93117229],"iteration":24,"passed_time":0.03532777117,"remaining_time":0.1059833135},
{"learn":[5.844857622],"iteration":25,"passed_time":0.0367860024,"remaining_time":0.1046986222},
{"learn":[5.771145213],"iteration":26,"passed_time":0.03833362403,"remaining_time":0.1036427613},
{"learn":[5.704018229],"iteration":27,"passed_time":0.03990111477,"remaining_time":0.1026028666},
{"learn":[5.665806474],"iteration":28,"passed_time":0.04144226496,"remaining_time":0.101462097},
{"learn":[5.616500369],"iteration":29,"passed_time":0.04291589982,"remaining_time":0.1001370996},
{"learn":[5.558023666],"iteration":30,"passed_time":0.04420685426,"remaining_time":0.09839590141},
{"learn":[5.510080976],"iteration":31,"passed_time":0.0455090138,"remaining_time":0.09670665433},
{"learn":[5.468747792],"iteration":32,"passed_time":0.04685064343,"remaining_time":0.09512100333},
{"learn":[5.429275534],"iteration":33,"passed_time":0.04829357618,"remaining_time":0.09374635376},
{"learn":[5.402117324],"iteration":34,"passed_time":0.04964037894,"remaining_time":0.09218927518},
{"learn":[5.367635151],"iteration":35,"passed_time":0.05100934855,"remaining_time":0.09068328631},
{"learn":[5.345181232],"iteration":36,"passed_time":0.05254914846,"remaining_time":0.0894755771},
{"learn":[5.319151269],"iteration":37,"passed_time":0.05413615629,"remaining_time":0.08832741289},
{"learn":[5.296134146],"iteration":38,"passed_time":0.0555217404,"remaining_time":0.08684169653},
{"learn":[5.269629003],"iteration":39,"passed_time":0.05682153961,"remaining_time":0.08523230942},
{"learn":[5.251147059],"iteration":40,"passed_time":0.05818942829,"remaining_time":0.08373600656},
{"learn":[5.248003302],"iteration":41,"passed_time":0.0587806148,"remaining_time":0.08117322996},
{"learn":[5.232376509],"iteration":42,"passed_time":0.06021035305,"remaining_time":0.07981372381},
{"learn":[5.213524255],"iteration":43,"passed_time":0.06170265205,"remaining_time":0.07853064807},
{"learn":[5.189691584],"iteration":44,"passed_time":0.06372652192,"remaining_time":0.07788797124},
{"learn":[5.166052198],"iteration":45,"passed_time":0.06510527902,"remaining_time":0.07642793624},
{"learn":[5.140406659],"iteration":46,"passed_time":0.06659219106,"remaining_time":0.07509332184},
{"learn":[5.118929684],"iteration":47,"passed_time":0.06800991971,"remaining_time":0.07367741302},
{"learn":[5.108792602],"iteration":48,"passed_time":0.06934597455,"remaining_time":0.07217642249},
{"learn":[5.098141225],"iteration":49,"passed_time":0.07064412578,"remaining_time":0.07064412578},
{"learn":[5.085926393],"iteration":50,"passed_time":0.07194163198,"remaining_time":0.06912039151},
{"learn":[5.067816804],"iteration":51,"passed_time":0.07330923123,"remaining_time":0.06767005959},
{"learn":[5.049834901],"iteration":52,"passed_time":0.07487361384,"remaining_time":0.06639735567},
{"learn":[5.03838627],"iteration":53,"passed_time":0.07642296142,"remaining_time":0.06510104121},
{"learn":[5.033534248],"iteration":54,"passed_time":0.07733458793,"remaining_time":0.06327375376},
{"learn":[5.023726885],"iteration":55,"passed_time":0.07861299997,"remaining_time":0.06176735712},
{"learn":[5.01290392],"iteration":56,"passed_time":0.07996423516,"remaining_time":0.0603238967},
{"learn":[5.005569127],"iteration":57,"passed_time":0.08135819623,"remaining_time":0.05891455589},
{"learn":[4.989969032],"iteration":58,"passed_time":0.08285516629,"remaining_time":0.05757731895},
{"learn":[4.976762446],"iteration":59,"passed_time":0.08445120908,"remaining_time":0.05630080606},
{"learn":[4.967222715],"iteration":60,"passed_time":0.08598880932,"remaining_time":0.05497645186},
{"learn":[4.954407599],"iteration":61,"passed_time":0.0875933094,"remaining_time":0.05368622189},
{"learn":[4.942125056],"iteration":62,"passed_time":0.08897466428,"remaining_time":0.05225496156},
{"learn":[4.930230716],"iteration":63,"passed_time":0.09032311148,"remaining_time":0.05080675021},
{"learn":[4.921695642],"iteration":64,"passed_time":0.09171881386,"remaining_time":0.04938705362},
{"learn":[4.906405625],"iteration":65,"passed_time":0.09304487802,"remaining_time":0.04793220989},
{"learn":[4.894330248],"iteration":66,"passed_time":0.09434139898,"remaining_time":0.0464666592},
{"learn":[4.88211557],"iteration":67,"passed_time":0.09630805961,"remaining_time":0.04532143982},
{"learn":[4.877946398],"iteration":68,"passed_time":0.09786454609,"remaining_time":0.0439681294},
{"learn":[4.863182126],"iteration":69,"passed_time":0.099826818,"remaining_time":0.042782922},
{"learn":[4.84646533],"iteration":70,"passed_time":0.1016853296,"remaining_time":0.04153344448},
{"learn":[4.838014752],"iteration":71,"passed_time":0.1030667542,"remaining_time":0.04008151551},
{"learn":[4.82981137],"iteration":72,"passed_time":0.1044203633,"remaining_time":0.03862123026},
{"learn":[4.817094767],"iteration":73,"passed_time":0.1057977228,"remaining_time":0.03717217289},
{"learn":[4.808314151],"iteration":74,"passed_time":0.1073702361,"remaining_time":0.0357900787},
{"learn":[4.796235023],"iteration":75,"passed_time":0.1088578416,"remaining_time":0.0343761605},
{"learn":[4.784434534],"iteration":76,"passed_time":0.1103959297,"remaining_time":0.03297540758},
{"learn":[4.774402487],"iteration":77,"passed_time":0.1120064695,"remaining_time":0.03159156831},
{"learn":[4.76731896],"iteration":78,"passed_time":0.1135710913,"remaining_time":0.03018978376},
{"learn":[4.75934113],"iteration":79,"passed_time":0.1150561463,"remaining_time":0.02876403657},
{"learn":[4.754106378],"iteration":80,"passed_time":0.1166706677,"remaining_time":0.02736719367},
{"learn":[4.744002932],"iteration":81,"passed_time":0.1182354591,"remaining_time":0.02595412517},
{"learn":[4.731700554],"iteration":82,"passed_time":0.1197420075,"remaining_time":0.02452547143},
{"learn":[4.723284153],"iteration":83,"passed_time":0.121305972,"remaining_time":0.02310589942},
{"learn":[4.712232782],"iteration":84,"passed_time":0.1240966927,"remaining_time":0.02189941636},
{"learn":[4.703046867],"iteration":85,"passed_time":0.127085494,"remaining_time":0.02068833623},
{"learn":[4.698601855],"iteration":86,"passed_time":0.1285061919,"remaining_time":0.01920207466},
{"learn":[4.692429407],"iteration":87,"passed_time":0.1300471838,"remaining_time":0.01773370689},
{"learn":[4.675027364],"iteration":88,"passed_time":0.1315821662,"remaining_time":0.01626296436},
{"learn":[4.662368584],"iteration":89,"passed_time":0.1329925516,"remaining_time":0.01477695017},
{"learn":[4.646206172],"iteration":90,"passed_time":0.1344209714,"remaining_time":0.01329438179},
{"learn":[4.641245848],"iteration":91,"passed_time":0.1359416205,"remaining_time":0.01182101048},
{"learn":[4.633900435],"iteration":92,"passed_time":0.1372797285,"remaining_time":0.01033288279},
{"learn":[4.624738236],"iteration":93,"passed_time":0.138603528,"remaining_time":0.008847033703},
{"learn":[4.612798287],"iteration":94,"passed_time":0.1400241817,"remaining_time":0.007369693773},
{"learn":[4.605222001],"iteration":95,"passed_time":0.1415006837,"remaining_time":0.00589586182},
{"learn":[4.601725912],"iteration":96,"passed_time":0.1431296265,"remaining_time":0.004426689479},
{"learn":[4.59722371],"iteration":97,"passed_time":0.1445250477,"remaining_time":0.002949490769},
{"learn":[4.580235665],"iteration":98,"passed_time":0.1459274082,"remaining_time":0.001474014224},
{"learn":[4.57591791],"iteration":99,"passed_time":0.1473016088,"remaining_time":0}
]}